derpibooru/VERSION
derpibooru/__init__.py
derpibooru/comment.py
derpibooru/helpers.py
derpibooru/image.py
derpibooru/query.py
derpibooru/request.py
derpibooru/search.py
derpibooru/sort.py
derpibooru/user.py
DerPyBooru_Nullforce-0.10.0.dist-info/LICENSE.txt
DerPyBooru_Nullforce-0.10.0.dist-info/METADATA
DerPyBooru_Nullforce-0.10.0.dist-info/WHEEL
DerPyBooru_Nullforce-0.10.0.dist-info/top_level.txt
DerPyBooru_Nullforce-0.10.0.dist-info/RECORD
