Metadata-Version: 2.1
Name: DerPyBooru-Nullforce
Version: 0.10.0
Summary: Python bindings for Derpibooru's API
Home-page: https://github.com/nullforce-public/DerPyBooru
Author: Nullforce
Author-email: glenngit@nullforce.com
License: Simplified BSD License
Keywords: derpibooru ponies pony mlp
Platform: any
Classifier: Development Status :: 5 - Production/Stable
Classifier: Intended Audience :: Developers
Classifier: Operating System :: OS Independent
Classifier: License :: OSI Approved :: BSD License
Classifier: Topic :: Software Development :: Libraries :: Python Modules
Classifier: Programming Language :: Python :: 2.7
Classifier: Programming Language :: Python :: 3
Classifier: Programming Language :: Python :: 3.5
Classifier: Programming Language :: Python :: 3.6
Classifier: Programming Language :: Python :: 3.7
Requires-Dist: requests
